uapi/__init__.py
uapi/client.py
uapi/errors.py
uapi_sdk_python-0.1.5.dist-info/METADATA
uapi_sdk_python-0.1.5.dist-info/WHEEL
uapi_sdk_python-0.1.5.dist-info/top_level.txt
uapi_sdk_python-0.1.5.dist-info/RECORD
