Metadata-Version: 2.4
Name: uapi-sdk-python
Version: 0.1.5
Summary: Idiomatic UAPI SDK for Python
Author-email: UAPI <dev@uapis.cn>
Requires-Python: >=3.9
Requires-Dist: httpx>=0.24.1
Provides-Extra: dev
Requires-Dist: pytest; extra == "dev"
Requires-Dist: mypy; extra == "dev"
Requires-Dist: black; extra == "dev"
Requires-Dist: isort; extra == "dev"
